{
	"texture_data": {
		"simplynetwork_green_barrier": {
			"textures": "textures/blocks/green_barrier"
		},
		"simplynetwork_light_blue_barrier": {
			"textures": "textures/blocks/light_blue_barrier"
		},
		"simplynetwork_magenta_barrier": {
			"textures": "textures/blocks/magenta_barrier"
		},
		"simplynetwork_orange_barrier": {
			"textures": "textures/blocks/orange_barrier"
		},
		"simplynetwork_light_blue_planks": {
			"textures": "textures/blocks/light_blue_planks"
		},
		"simplynetwork_green_planks": {
			"textures": "textures/blocks/green_planks"
		},
		"simplynetwork_magenta_planks": {
			"textures": "textures/blocks/magenta_planks"
		},
		"simplynetwork_orange_planks": {
			"textures": "textures/blocks/orange_planks"
		},
		"simplynetwork_white_planks": {
			"textures": "textures/blocks/white_planks"
		},
		"simplynetwork_white_bricks": {
			"textures": "textures/blocks/white_bricks"
		}
	}
}